ardt/__about__.py
ardt/__init__.py
ardt/ardt_utils.py
ardt/config.py
ardt/datasets/AERDataset.py
ardt/datasets/AERDerivedSignal.py
ardt/datasets/AERTrial.py
ardt/datasets/AERTrialFilter.py
ardt/datasets/MultiDataset.py
ardt/datasets/__init__.py
ardt/datasets/ascertain/AscertainDataset.py
ardt/datasets/ascertain/AscertainTrial.py
ardt/datasets/ascertain/__init__.py
ardt/datasets/cuads/CuadsDataset.py
ardt/datasets/cuads/CuadsTrial.py
ardt/datasets/cuads/__init__.py
ardt/datasets/dreamer/DreamerDataset.py
ardt/datasets/dreamer/DreamerTrial.py
ardt/datasets/dreamer/__init__.py
ardt/datasets/ml/TFDatasetWrapper.py
ardt/datasets/ml/TFRecordDatasetGenerator.py
ardt/datasets/ml/TorchDatasetWrapper.py
ardt/datasets/ml/__init__.py
ardt/derived/__init__.py
ardt/derived/ibi.py
ardt/preprocessors/ChannelSelector.py
ardt/preprocessors/FixedDuration.py
ardt/preprocessors/LowPass.py
ardt/preprocessors/MedianFilter.py
ardt/preprocessors/MedianFilterWithLowPass.py
ardt/preprocessors/MinMaxScaler.py
ardt/preprocessors/MultiChannelZScoreNorm.py
ardt/preprocessors/NK2ECGCleaner.py
ardt/preprocessors/NotchFilter.py
ardt/preprocessors/Resample.py
ardt/preprocessors/SignalPreprocessor.py
ardt/preprocessors/__init__.py
ardt-0.6.1.dist-info/METADATA
ardt-0.6.1.dist-info/WHEEL
ardt-0.6.1.dist-info/licenses/LICENSE
ardt-0.6.1.dist-info/RECORD
