Metadata-Version: 2.4
Name: ardt
Version: 0.6.1
Summary: Affective Research Dataset Tookit (ARDT): an extensible utility package for working with AER Datasets such as ASCERTAIN, CUADS, DREAMER and more
Project-URL: Homepage, https://affects.ai/ardt
Project-URL: Issues, https://github.com/affectsai/ardt/issues
Project-URL: Source, https://github.com/affectsai/ardt
Author-email: "Timothy C. Sweeney-Fanelli" <tim@affects.ai>
Maintainer-email: "Timothy C. Sweeney-Fanelli" <tim@affects.ai>
License-Expression: CC-BY-NC-SA-4.0
License-File: LICENSE
Classifier: Development Status :: 3 - Alpha
Classifier: Programming Language :: Python :: 3
Requires-Python: >=3.10
Requires-Dist: ijson
Requires-Dist: keras>=3.8.0
Requires-Dist: neurokit2
Requires-Dist: numpy
Requires-Dist: pyyaml
Requires-Dist: scikit-learn
Requires-Dist: scipy
Requires-Dist: tensorboard>=2.17.0
Requires-Dist: tensorflow>=2.17.0
